<?xml version="1.0" encoding="utf-8"?>
<odoo>
    <record id="pos_payment_method_view_form_inherit_pos_telebirr" model="ir.ui.view">
        <field name="name">pos.payment.method.form.inherit.telebirr</field>
        <field name="model">pos.payment.method</field>
        <field name="inherit_id" ref="point_of_sale.pos_payment_method_view_form"/>
        <field name="arch" type="xml">
            <xpath expr="//field[@name='journal_id']" position="after">
                <field name="telebirr_url" invisible="use_payment_terminal != 'telebirr'" required="use_payment_terminal == 'telebirr'"/>
                <field name="telebirr_api_key" invisible="use_payment_terminal != 'telebirr'" required="use_payment_terminal == 'telebirr'"/>
                <field name="telebirr_app_id" invisible="use_payment_terminal != 'telebirr'" required="use_payment_terminal == 'telebirr'"/>
                <field name="telebirr_payment" invisible="use_payment_terminal != 'telebirr'" required="use_payment_terminal == 'telebirr'"/>
            </xpath>
        </field>
    </record>
</odoo>
